{
  "Shaheer": {
    "weight_class": "LIGHT-HEAVYWEIGHT",
    "weight": "75 kg",
    "record": "2-0-0",
    "last_fight": "GFC 005",
    "last_fight_result": "Shaheer beat Mazhar 3 rounds to 0",
    "pound_for_pound_rank": 1,
    "total_fouls": 1,
    "current_champion": false,
    "former_champion": false,
    "total_rounds_won": 6,
    "total_rounds_lost": 0
  },
  "Mowahid": {
    "weight_class": "LIGHTWEIGHT",
    "weight": "57 kg",
    "record": "1-0-0",
    "last_fight": "GFC 001",
    "last_fight_result": "Mowahid beat Mazhar 3 rounds to 2",
    "pound_for_pound_rank": 3,
    "total_fouls": 0,
    "current_champion": false,
    "former_champion": true,
    "total_rounds_won": 3,
    "total_rounds_lost": 2
  },
  "Mazin": {
    "weight_class": "LIGHTWEIGHT",
    "weight": "52 kg",
    "record": "1-0-0",
    "last_fight": "GFC 002",
    "last_fight_result": "Mazin beat Ubaid 2 rounds to 1",
    "pound_for_pound_rank": 2,
    "total_fouls": 1,
    "current_champion": true,
    "former_champion": false,
    "total_rounds_won": 2,
    "total_rounds_lost": 1
  },
  "Ayaan": {
    "weight_class": "LIGHTWEIGHT",
    "weight": "52 kg",
    "record": "1-1-0",
    "last_fight": "GFC 006",
    "last_fight_result": "Ayaan lost to Mazhar 1 round to 2",
    "pound_for_pound_rank": 6,
    "total_fouls": 3,
    "current_champion": false,
    "former_champion": false,
    "total_rounds_won": 2,
    "total_rounds_lost": 2
  },
  "Ubaid": {
    "weight_class": "MIDDLEWEIGHT",
    "weight": "65 kg",
    "record": "1-2-0",
    "last_fight": "GFC 004",
    "last_fight_result": "Ubaid beat Mazhar 2 rounds to 1",
    "pound_for_pound_rank": 4,
    "total_fouls": 4,
    "current_champion": false,
    "former_champion": false,
    "total_rounds_won": 3,
    "total_rounds_lost": 6
  },
  "Daniyal": {
    "weight_class": "HEAVYWEIGHT",
    "weight": "95 kg",
    "record": "0-0-0",
    "last_fight": null,
    "last_fight_result": null,
    "pound_for_pound_rank": null,
    "total_fouls": 0,
    "current_champion": false,
    "former_champion": false,
    "total_rounds_won": 0,
    "total_rounds_lost": 0
  },
  "Musa": {
    "weight_class": "LIGHT-HEAVYWEIGHT",
    "weight": "75 kg",
    "record": "0-0-0",
    "last_fight": null,
    "last_fight_result": null,
    "pound_for_pound_rank": null,
    "total_fouls": 0,
    "current_champion": false,
    "former_champion": false,
    "total_rounds_won": 0,
    "total_rounds_lost": 0
  },
  "Sharafat": {
    "weight_class": "LIGHTWEIGHT",
    "weight": "50 kg",
    "record": "0-0-0",
    "last_fight": null,
    "last_fight_result": null,
    "pound_for_pound_rank": null,
    "total_fouls": 0,
    "current_champion": false,
    "former_champion": false,
    "total_rounds_won": 0,
    "total_rounds_lost": 0
  },
  "Mazhar": {
    "weight_class": "LIGHT-HEAVYWEIGHT",
    "weight": "75 kg",
    "record": "1-4-0",
    "last_fight": "GFC 006",
    "last_fight_result": "Mazhar Beat Ayaan 2 rounds to 1",
    "pound_for_pound_rank": 5,
    "total_fouls": 9,
    "current_champion": false,
    "former_champion": false,
    "total_rounds_won": 5,
    "total_rounds_lost": 10
  }
}